etherscan/__init__.py
etherscan/etherscan.py
etherscan/configs/GOERLI-stable.json
etherscan/configs/KOVAN-stable.json
etherscan/configs/MAIN-stable.json
etherscan/configs/RINKEBY-stable.json
etherscan/configs/ROPSTEN-stable.json
etherscan/configs/__init__.py
etherscan/enums/__init__.py
etherscan/enums/actions_enum.py
etherscan/enums/fields_enum.py
etherscan/enums/modules_enum.py
etherscan/enums/tags_enum.py
etherscan/modules/__init__.py
etherscan/modules/accounts.py
etherscan/modules/blocks.py
etherscan/modules/contracts.py
etherscan/modules/gastracker.py
etherscan/modules/pro.py
etherscan/modules/proxy.py
etherscan/modules/stats.py
etherscan/modules/tokens.py
etherscan/modules/transactions.py
etherscan/utils/__init__.py
etherscan/utils/conversions.py
etherscan/utils/parsing.py
etherscan_python_api-2.2.0.dist-info/LICENSE
etherscan_python_api-2.2.0.dist-info/METADATA
etherscan_python_api-2.2.0.dist-info/WHEEL
etherscan_python_api-2.2.0.dist-info/top_level.txt
etherscan_python_api-2.2.0.dist-info/RECORD
