Metadata-Version: 2.1
Name: etherscan-python-api
Version: 2.2.0
Summary: A minimal, yet complete, python API for etherscan.io.
Home-page: https://github.com/pcko1/etherscan-python
Author: Panagiotis-Christos Kotsias
Author-email: kotsias.pan@gmail.com
License: MIT
License-File: LICENSE
Requires-Dist: requests
